sqlviewer_example/__init__.py
sqlviewer_example/example.py
sqlviewer_example-0.1.0.dist-info/METADATA
sqlviewer_example-0.1.0.dist-info/WHEEL
sqlviewer_example-0.1.0.dist-info/entry_points.txt
sqlviewer_example-0.1.0.dist-info/top_level.txt
sqlviewer_example-0.1.0.dist-info/RECORD
