Metadata-Version: 2.1
Name: sqlviewer-example
Version: 0.1.0
Summary: Example connector to sqlviewer to demonstrate extendibility
Home-page: UNKNOWN
Author: Kieran Bacon
Author-email: kieran.bacon@outlook.com
License: UNKNOWN
Platform: UNKNOWN
Requires-Dist: sqlviewer
